.coverage
.gitignore
AUTHORS
LICENSE
MANIFEST.in
README.md
circle.yml
setup.cfg
setup.py
tox.ini
scrapy_job_parameters.egg-info/PKG-INFO
scrapy_job_parameters.egg-info/SOURCES.txt
scrapy_job_parameters.egg-info/dependency_links.txt
scrapy_job_parameters.egg-info/requires.txt
scrapy_job_parameters.egg-info/top_level.txt
scrapyjobparameters/__init__.py
scrapyjobparameters/extension.py
tests/test_extension.py